{
  "contacts": [
    {
      "firstName": "Mr",
      "lastName": "One",
      "street": "33 first street",
      "city": "city of thisone",
      "email": "thisone@one.com",
      "linkdin": "oneLink",
      "twitter": "oneTwit",
      "id": 1,
      "contactType": "personal"
    },
    {
      "firstName": "Jim",
      "lastName": "Jones",
      "street": "23 Kool Aid Rise",
      "city": "New York",
      "email": "Jim@takemydrink.com",
      "linkdin": "linkdin/jj",
      "twitter": "twitter/jj",
      "id": 2,
      "contactType": "personal"
    },
    {
      "firstName": "Matt",
      "lastName": "Holt",
      "street": "32 meStreet",
      "city": "meTown",
      "email": "me@me.co.uk",
      "linkdin": "linkdin/me",
      "twitter": "twitter/me",
      "contactType": "work",
      "id": 3
    }
  ],
  "meetings": [
    {
      "date": "303030",
      "time": "2.30 pm",
      "location": "12 first street",
      "contactId": "1",
      "id": 1
    },
    {
      "date": "120343",
      "time": "some time",
      "location": "who knows",
      "contactId": "2",
      "id": 2
    },
    {
      "date": "232323",
      "time": "23.23",
      "location": "117 23rd street",
      "contactId": "3",
      "id": 3
    }
  ]
}